README.txt
scw.py
setup.py
scw.egg-info/PKG-INFO
scw.egg-info/SOURCES.txt
scw.egg-info/dependency_links.txt
scw.egg-info/top_level.txt