Metadata-Version: 1.0
Name: scw
Version: 1.1.2
Summary: An implementation of Exact Soft Confidence-Weighted Learning
Home-page: https://pypi.python.org/pypi/scw
Author: Ishita Takeshi
Author-email: ishitah.takeshi@gmail.com
License: MIT
Keywords: Exact Soft Confidence-Weighted Learning
Platform: UNKNOWN
